{
  "type": "minecraft:add",
  "argument1": -1.0,
  "argument2": {
    "type": "minecraft:mul",
    "argument1": {
      "type": "minecraft:abs",
      "argument": {
        "type": "minecraft:add",
        "argument1": {
          "type": "more_dfs:mod",
          "dividend": {
            "type": "minecraft:abs",
            "argument": {
              "type": "minecraft:add",
              "argument1": {
                "type": "more_dfs:z"
              },
              "argument2": -2000
            }
          },
          "divisor": 8000
        },
        "argument2": -4000.0
      }
    },
    "argument2": 0.0005
  }
}
